PrevMed/__init__.py
PrevMed/__main__.py
prevmed-0.9.8.dist-info/licenses/LICENSE
prevmed-0.9.8.dist-info/METADATA
prevmed-0.9.8.dist-info/WHEEL
prevmed-0.9.8.dist-info/entry_points.txt
prevmed-0.9.8.dist-info/top_level.txt
prevmed-0.9.8.dist-info/RECORD
