Metadata-Version: 2.4
Name: PrevMed
Version: 0.9.8
Summary: Générateur dynamique de questionnaires cliniques avec interface Gradio et scoring automatisé en R ou Python
Home-page: https://github.com/PrevMedOrg/PrevMed/
Keywords: prevention,preventive,medical,care,health,formulaires,surveys,clinical,clinique,APHP,AP-HP,hopital,hospital,healthcare,patients
Classifier: Programming Language :: Python :: 3
Classifier: Operating System :: OS Independent
Requires-Python: ==3.13
License-File: LICENSE
Requires-Dist: reportlab==4.4.4
Requires-Dist: gradio==5.49.1
Requires-Dist: loguru==0.7.3
Requires-Dist: pyr2==2.0.0
Requires-Dist: pyyaml==6.0.3
Requires-Dist: rpy2[all]==3.6.4
Requires-Dist: filelock==3.20.0
Dynamic: classifier
Dynamic: description
Dynamic: description-content-type
Dynamic: home-page
Dynamic: keywords
Dynamic: license-file
Dynamic: requires-dist
Dynamic: requires-python
Dynamic: summary
